modules/analytics.py
modules/blacklist.py
modules/blog_posts.py
modules/checkout.py
modules/coupons.py
modules/crypto_wallet.py
modules/custom_fields.py
modules/customers.py
modules/domains.py
modules/feedbacks.py
modules/groups.py
modules/images.py
modules/invoices.py
modules/notifications.py
modules/payment_methods.py
modules/products.py
modules/shops.py
modules/tickets.py
pysellauth-0.1.1.dist-info/METADATA
pysellauth-0.1.1.dist-info/WHEEL
pysellauth-0.1.1.dist-info/top_level.txt
pysellauth-0.1.1.dist-info/RECORD
