Metadata-Version: 2.4
Name: pysellauth
Version: 0.1.1
Summary: Python wrapper for the SellAuth API
Author-email: Useless <bot40games2@example.com>
License: MIT
Project-URL: Homepage, https://github.com/TheUselessCreator/pysellauth
Project-URL: Documentation, https://github.com/TheUselessCreator/pysellauth#readme
Project-URL: Bug_Tracker, https://github.com/TheUselessCreator/pysellauth/issues
Requires-Python: >=3.8
Requires-Dist: requests>=2.0.0
